cBASEdzne/__init__.py
cBASEdzne/__main__.py
cBASEdzne/tests/__init__.py
cBASEdzne/tests/test_1984.py
cBASEdzne-0.0.1.dev0.dist-info/LICENSE.txt
cBASEdzne-0.0.1.dev0.dist-info/METADATA
cBASEdzne-0.0.1.dev0.dist-info/WHEEL
cBASEdzne-0.0.1.dev0.dist-info/top_level.txt
cBASEdzne-0.0.1.dev0.dist-info/RECORD
