Metadata-Version: 2.1
Name: cBASEdzne
Version: 0.0.1.dev0
Summary: cBASEdzne
Author-email: Johannes <johannes-programming@mailfence.com>
License: The MIT License (MIT)
Project-URL: Documentation, https://pypi.org/project/cBASEdzne
Project-URL: Download, https://pypi.org/project/cBASEdzne/#files
Project-URL: Source, https://github.com/johannes-programming/cBASEdzne
Classifier: Development Status :: 2 - Pre-Alpha
Classifier: License :: OSI Approved :: MIT License
Classifier: Programming Language :: Python
Classifier: Programming Language :: Python :: 3
Classifier: Programming Language :: Python :: 3 :: Only
Requires-Python: >=3.12.7
License-File: LICENSE.txt
